[
  {
    "fullName": "Jamie King (C)",
    "position": "Goalkeeper",
    "imageUrl": "/images/players/jamie.jpeg"
  },
  {
    "fullName": "Martyn McDonnell",
    "position": "Defender",
    "imageUrl": "/images/players/martyn.jpeg"
  },
  {
    "fullName": "Niall McInerney",
    "position": "Defender",
    "imageUrl": "/images/players/niall.jpeg"
  },
  {
    "fullName": "Steve O'Hara",
    "position": "Defender",
    "imageUrl": "/images/players/steve.jpeg"
  },
  {
    "fullName": "Steven Derby",
    "position": "Defender",
    "imageUrl": "/images/players/steven.jpeg"
  },
  {
    "fullName": "Nicholas Boyd",
    "position": "Defender",
    "imageUrl": "/images/players/nick.jpeg"
  },
  {
    "fullName": "Jonathan Jones",
    "position": "Defender",
    "imageUrl": "/images/players/jj.jpeg"
  },
  {
    "fullName": "Jack Caine",
    "position": "Defender",
    "imageUrl": "/images/players/jack.jpeg"
  },
  {
    "fullName": "Ryan Wharry",
    "position": "Defender",
    "imageUrl": "/images/players/placeholderplayer.png"
  },
  {
    "fullName": "James Bainbridge",
    "position": "Midfielder",
    "imageUrl": "/images/players/jamesb.jpeg"
  },
  {
    "fullName": "Eugelito Troyo",
    "position": "Midfielder",
    "imageUrl": "/images/players/eugelito.jpeg"
  },
  {
    "fullName": "Guillermo Álvarez Narciandi",
    "position": "Midfielder",
    "imageUrl": "/images/players/guillermo.jpeg"
  },
  {
    "fullName": "James Hewitt",
    "position": "Midfielder",
    "imageUrl": "/images/players/jamesh.jpeg"
  },
  {
    "fullName": "Jordan Thompson",
    "position": "Forward",
    "imageUrl": "/images/players/jordan.jpeg"
  },
  {
    "fullName": "Aaron O'Donovan",
    "position": "Midfielder",
    "imageUrl": "/images/players/steven.jpeg"
  },
  {
    "fullName": "Edgar Texeira",
    "position": "Midfielder",
    "imageUrl": "/images/players/edgar.jpeg"
  },
  {
    "fullName": "Juan Jesus Texeira",
    "position": "Midfielder",
    "imageUrl": "/images/players/juan.jpeg"
  },
  {
    "fullName": "Nicky Joe Sibanda",
    "position": "Midfielder",
    "imageUrl": "/images/players/joe.jpeg"
  },
  {
    "fullName": "Eoin Devenny",
    "position": "Forward",
    "imageUrl": "/images/players/eoin.jpeg"
  },
  {
    "fullName": "Iñigo Rodriguez Garcia",
    "position": "Forward",
    "imageUrl": "/images/players/inigo.jpeg"
  },
  {
    "fullName": "Diarmuid Waide",
    "position": "Forward",
    "imageUrl": "/images/players/diarmuid.jpeg"
  },
  {
    "fullName": "Mark Kavanagh",
    "position": "Forward",
    "imageUrl": "/images/players/placeholderplayer.png"
  }
]
