[
  {
    "fullName": "Jamie King (C)",
    "position": "Goalkeeper"
  },
  {
    "fullName": "Aaron Crawford",
    "position": "Defender"
  },
  {
    "fullName": "Marty McDonnell",
    "position": "Defender"
  },
  {
    "fullName": "Ryan Wharry",
    "position": "Defender"
  },
  {
    "fullName": "Daniel Oluwasanmi Ajayi",
    "position": "Defender"
  },
  {
    "fullName": "Aaron McKee",
    "position": "Defender"
  },
  {
    "fullName": "Niall McInerney",
    "position": "Defender"
  },
  {
    "fullName": "Steve O'Hara",
    "position": "Defender"
  },
  {
    "fullName": "James Bainbridge",
    "position": "Defender"
  },
  {
    "fullName": "Scott Evanson",
    "position": "Midfielder"
  },
  {
    "fullName": "Dylan Geraghty",
    "position": "Midfielder"
  },
  {
    "fullName": "Mark Kavanagh",
    "position": "Midfielder"
  },
  {
    "fullName": "Eugelito Troyo",
    "position": "Midfielder"
  },
  {
    "fullName": "Guillermo Álvarez Narciandi",
    "position": "Midfielder"
  },
  {
    "fullName": "Steven Darby",
    "position": "Midfielder"
  },
  {
    "fullName": "James Hewitt",
    "position": "Midfielder"
  },
  {
    "fullName": "Jack Kerr",
    "position": "Midfielder"
  },
  {
    "fullName": "Iñigo Rodriguez",
    "position": "Forward"
  },
  {
    "fullName": "Diarmuid Waide",
    "position": "Forward"
  },
  {
    "fullName": "Eoin Devenny",
    "position": "Forward"
  },
  {
    "fullName": "Richard Winder",
    "position": "Forward"
  }
]
